pyMMF/__init__.py
pyMMF/core.py
pyMMF/functions.py
pyMMF/index_profile.py
pyMMF/logger.py
pyMMF/modes.py
pyMMF/solvers/SI.py
pyMMF/solvers/WKB.py
pyMMF/solvers/__init__.py
pyMMF/solvers/eig2D.py
pyMMF/solvers/radial.py
pyMMF/solvers/radial_legacy.py
pyMMF-0.6.dist-info/LICENSE
pyMMF-0.6.dist-info/METADATA
pyMMF-0.6.dist-info/WHEEL
pyMMF-0.6.dist-info/top_level.txt
pyMMF-0.6.dist-info/RECORD
